neighborly/__init__.py
neighborly/__version__.py
neighborly/config.py
neighborly/data_analysis.py
neighborly/data_collection.py
neighborly/datetime.py
neighborly/ecs.py
neighborly/inspection.py
neighborly/libraries.py
neighborly/life_event.py
neighborly/loaders.py
neighborly/py.typed
neighborly/simulation.py
neighborly/systems.py
neighborly/tracery.py
neighborly/components/__init__.py
neighborly/components/business.py
neighborly/components/character.py
neighborly/components/location.py
neighborly/components/relationship.py
neighborly/components/residence.py
neighborly/components/settlement.py
neighborly/components/skills.py
neighborly/components/spawn_table.py
neighborly/components/stats.py
neighborly/components/traits.py
neighborly/defs/__init__.py
neighborly/defs/base_types.py
neighborly/defs/defaults.py
neighborly/defs/definition_compiler.py
neighborly/effects/__init__.py
neighborly/effects/base_types.py
neighborly/effects/effects.py
neighborly/events/__init__.py
neighborly/events/defaults.py
neighborly/helpers/__init__.py
neighborly/helpers/business.py
neighborly/helpers/character.py
neighborly/helpers/content_selection.py
neighborly/helpers/location.py
neighborly/helpers/relationship.py
neighborly/helpers/residence.py
neighborly/helpers/settlement.py
neighborly/helpers/skills.py
neighborly/helpers/stats.py
neighborly/helpers/traits.py
neighborly/plugins/__init__.py
neighborly/plugins/default_character_names.py
neighborly/plugins/default_events.py
neighborly/plugins/default_settlement_names.py
neighborly/plugins/default_traits.py
neighborly/plugins/data/character_names.tracery.json
neighborly/plugins/data/settlement_names.tracery.json
neighborly/plugins/data/traits.json
neighborly/preconditions/__init__.py
neighborly/preconditions/base_types.py
neighborly/preconditions/defaults.py
neighborly-2.5.0.dist-info/LICENSE
neighborly-2.5.0.dist-info/METADATA
neighborly-2.5.0.dist-info/WHEEL
neighborly-2.5.0.dist-info/top_level.txt
neighborly-2.5.0.dist-info/RECORD
