Metadata-Version: 2.1
Name: neighborly
Version: 2.5.0
Summary: A narrative-focused agent-based settlement simulation framework.
Author-email: Shi Johnson-Bey <shijbey@gmail.com>
Project-URL: Homepage, https://github.com/ShiJbey/neighborly
Project-URL: Bug Tracker, https://github.com/ShiJbey/neighborly/issues
Project-URL: Repository, https://github.com/ShiJBey/neighborly.git
Project-URL: Changelog, https://github.com/ShiJbey/neighborly/blob/main/CHANGELOG.md
Project-URL: Documentation, https://neighborly.readthedocs.io/en/latest/
Keywords: social simulation,games,simulation,artificial intelligence,agent-based modeling,multiagent systems,emergent narrative,narrative generation,interactive storytelling,settlement simulation
Classifier: Intended Audience :: Developers
Classifier: Intended Audience :: Science/Research
Classifier: License :: OSI Approved :: MIT License
Classifier: Operating System :: OS Independent
Classifier: Programming Language :: Python :: 3 :: Only
Classifier: Programming Language :: Python :: 3.8
Classifier: Programming Language :: Python :: 3.9
Classifier: Programming Language :: Python :: 3.10
Classifier: Programming Language :: Python :: 3.11
Classifier: Programming Language :: Python :: 3.12
Classifier: Topic :: Games/Entertainment :: Simulation
Classifier: Topic :: Scientific/Engineering
Classifier: Topic :: Scientific/Engineering :: Artificial Intelligence
Classifier: Topic :: Scientific/Engineering :: Artificial Life
Classifier: Topic :: Sociology
Classifier: Topic :: Software Development :: Libraries
Classifier: Topic :: Software Development :: Libraries :: Application Frameworks
Classifier: Typing :: Typed
Requires-Python: >=3.8
License-File: LICENSE
Requires-Dist: esper ==2.*
Requires-Dist: ordered-set ==4.*
Requires-Dist: tracery3 ==1.*
Requires-Dist: polars ==0.19.*
Requires-Dist: tabulate ==0.9.*
Requires-Dist: PyYAML ==6.0.*
Requires-Dist: tqdm ==4.*
Requires-Dist: pydantic ==2.*
Provides-Extra: development
Requires-Dist: isort ; extra == 'development'
Requires-Dist: black ; extra == 'development'
Requires-Dist: black[d] ; extra == 'development'
Requires-Dist: black[jupyter] ; extra == 'development'
Requires-Dist: build ; extra == 'development'
Requires-Dist: pytest ; extra == 'development'
Requires-Dist: pytest-cov ; extra == 'development'
Requires-Dist: sphinx ; extra == 'development'
Requires-Dist: sphinx-rtd-theme ; extra == 'development'
Provides-Extra: samples
Requires-Dist: jupyterlab ; extra == 'samples'
Requires-Dist: matplotlib ; extra == 'samples'
Requires-Dist: ipywidgets ; extra == 'samples'
